rename_clean.py
rename_clean-1.4.dist-info/METADATA
rename_clean-1.4.dist-info/WHEEL
rename_clean-1.4.dist-info/entry_points.txt
rename_clean-1.4.dist-info/top_level.txt
rename_clean-1.4.dist-info/RECORD
