Metadata-Version: 2.4
Name: rename-clean
Version: 1.4
Summary: Utility to replace undesirable characters in Linux file names
Author-email: Mark Blakeney <mark.blakeney@bullet-systems.net>
License-Expression: GPL-3.0-or-later
Project-URL: Homepage, https://github.com/bulletmark/rename-clean
Keywords: rename,mv
Classifier: Programming Language :: Python :: 3
Requires-Python: >=3.8
Requires-Dist: argparse-from-file
